{
  "gopherProxySet": "false",
  "awt.toolkit": "sun.lwawt.macosx.LWCToolkit",
  "java.specification.version": "10",
  "file.encoding.pkg": "sun.io",
  "sun.cpu.isalist": "",
  "sun.jnu.encoding": "UTF-8",
  "java.class.path": "build/libs/cne-precourse-drills.jar",
  "java.vm.vendor": "\"Oracle Corporation\"",
  "sun.arch.data.model": "64",
  "java.vendor.url": "http://java.oracle.com/",
  "user.timezone": "",
  "os.name": "Mac OS X",
  "java.vm.specification.version": "10",
  "sun.java.launcher": "SUN_STANDARD",
  "user.country": "US",
  "sun.boot.library.path": "/Library/Java/JavaVirtualMachines/jdk-10.0.2.jdk/Contents/Home/lib",
  "sun.java.command": "build/libs/cne-precourse-drills.jar",
  "http.nonProxyHosts": "local|*.local|169.254/16|*.169.254/16",
  "jdk.debug": "release",
  "sun.cpu.endian": "little",
  "user.home": "/Users/trainer3",
  "user.language": "en",
  "java.specification.vendor": "Oracle Corporation",
  "java.version.date": "2018-07-17",
  "java.home": "/Library/Java/JavaVirtualMachines/jdk-10.0.2.jdk/Contents/Home",
  "file.separator": "/",
  "java.vm.compressedOopsMode": "Zero based",
  "line.separator": "\n",
  "java.specification.name": "Java Platform API Specification",
  "java.vm.specification.vendor": "Oracle Corporation",
  "java.awt.graphicsenv": "sun.awt.CGraphicsEnvironment",
  "sun.management.compiler": "HotSpot 64-Bit Tiered Compilers",
  "ftp.nonProxyHosts": "local|*.local|169.254/16|*.169.254/16",
  "java.runtime.version": "10.0.2+13",
  "user.name": "trainer3",
  "path.separator": ":",
  "os.version": "10.12.3",
  "java.runtime.name": "Java(TM) SE Runtime Environment",
  "file.encoding": "UTF-8",
  "java.vm.name": "Java HotSpot(TM) 64-Bit Server VM",
  "java.vendor.version": "18.3",
  "java.vendor.url.bug": "http://bugreport.java.com/bugreport/",
  "java.io.tmpdir": "/var/folders/hc/1myvfjr95slgghz4jytcl3r40000gn/T/",
  "java.version": "10.0.2",
  "user.dir": "/Users/trainer3/Documents/Galvanize/cne-precourse-drills",
  "os.arch": "x86_64",
  "java.vm.specification.name": "Java Virtual Machine Specification",
  "java.awt.printerjob": "sun.lwawt.macosx.CPrinterJob",
  "sun.os.patch.level": "unknown",
  "java.library.path": "/Users/trainer3/Library/Java/Extensions:/Library/Java/Extensions:/Network/Library/Java/Extensions:/System/Library/Java/Extensions:/usr/lib/java:.",
  "java.vendor": "Oracle Corporation",
  "java.vm.info": "mixed mode",
  "java.vm.version": "10.0.2+13",
  "sun.io.unicode.encoding": "UnicodeBig",
  "java.class.version": "54.0",
  "socksNonProxyHosts": "local|*.local|169.254/16|*.169.254/16"
}
